itmo_routespd/__init__.py
itmo_routespd/BaseRouter.py
itmo_routespd/Data.py
itmo_routespd/DetailedRouter.py
itmo_routespd/dijkstra/__init__.py
itmo_routespd/dijkstra/Graph.py
itmo_routespd/dijkstra/Node.py
itmo_routespd/example.py
itmo_routespd/funcs.py
itmo_routespd-1.0.0.dist-info/WHEEL
itmo_routespd-1.0.0.dist-info/METADATA
itmo_routespd-1.0.0.dist-info/RECORD
